{
  "version": 1,
  "generatedAt": "2026-06-28T05:12:37.835Z",
  "items": [
    {
      "id": "auto_weibo_38cda454",
      "title": "习近平再次强调这条红线",
      "url": "https://s.weibo.com/weibo?q=%23%E4%B9%A0%E8%BF%91%E5%B9%B3%E5%86%8D%E6%AC%A1%E5%BC%BA%E8%B0%83%E8%BF%99%E6%9D%A1%E7%BA%A2%E7%BA%BF%23",
      "platform": "weibo",
      "keywords": [],
      "collectedAt": "2026-06-28T05:12:33.618Z",
      "source": "weibo_hotSearch"
    },
    {
      "id": "auto_weibo_998f0b47",
      "title": "世界杯32强全名单",
      "url": "https://s.weibo.com/weibo?q=%23%E4%B8%96%E7%95%8C%E6%9D%AF32%E5%BC%BA%E5%85%A8%E5%90%8D%E5%8D%95%23",
      "platform": "weibo",
      "keywords": [
        "新"
      ],
      "collectedAt": "2026-06-28T05:12:33.618Z",
      "source": "weibo_hotSearch"
    },
    {
      "id": "auto_weibo_8de279a3",
      "title": "伊朗出局",
      "url": "https://s.weibo.com/weibo?q=%23%E4%BC%8A%E6%9C%97%E5%87%BA%E5%B1%80%23",
      "platform": "weibo",
      "keywords": [
        "新"
      ],
      "collectedAt": "2026-06-28T05:12:33.618Z",
      "source": "weibo_hotSearch"
    },
    {
      "id": "auto_bilibili_37ac5e6e",
      "title": "T1 TLAW",
      "url": "https://search.bilibili.com/all?keyword=T1%20TLAW",
      "platform": "bilibili",
      "keywords": [],
      "collectedAt": "2026-06-28T05:12:35.447Z",
      "source": "bilibili_trending_ranking"
    },
    {
      "id": "auto_bilibili_aa3005d4",
      "title": "韩国队淘汰前还在墨西哥训练",
      "url": "https://search.bilibili.com/all?keyword=%E9%9F%A9%E5%9B%BD%E9%98%9F%E6%B7%98%E6%B1%B0%E5%89%8D%E8%BF%98%E5%9C%A8%E5%A2%A8%E8%A5%BF%E5%93%A5%E8%AE%AD%E7%BB%83",
      "platform": "bilibili",
      "keywords": [],
      "collectedAt": "2026-06-28T05:12:35.447Z",
      "source": "bilibili_trending_ranking"
    },
    {
      "id": "auto_bilibili_c85bc52d",
      "title": "牧神记",
      "url": "https://search.bilibili.com/all?keyword=%E7%89%A7%E7%A5%9E%E8%AE%B0",
      "platform": "bilibili",
      "keywords": [],
      "collectedAt": "2026-06-28T05:12:35.447Z",
      "source": "bilibili_trending_ranking"
    },
    {
      "id": "auto_weibo_d41734aa",
      "title": "全球最大人造太阳超导磁体在中国",
      "url": "https://s.weibo.com/weibo?q=%23%E5%85%A8%E7%90%83%E6%9C%80%E5%A4%A7%E4%BA%BA%E9%80%A0%E5%A4%AA%E9%98%B3%E8%B6%85%E5%AF%BC%E7%A3%81%E4%BD%93%E5%9C%A8%E4%B8%AD%E5%9B%BD%23",
      "platform": "weibo",
      "keywords": [
        "新"
      ],
      "collectedAt": "2026-06-28T05:12:33.618Z",
      "source": "weibo_hotSearch"
    },
    {
      "id": "auto_weibo_c297a739",
      "title": "诋毁袁隆平成果网红称大不了就进去",
      "url": "https://s.weibo.com/weibo?q=%23%E8%AF%8B%E6%AF%81%E8%A2%81%E9%9A%86%E5%B9%B3%E6%88%90%E6%9E%9C%E7%BD%91%E7%BA%A2%E7%A7%B0%E5%A4%A7%E4%B8%8D%E4%BA%86%E5%B0%B1%E8%BF%9B%E5%8E%BB%23",
      "platform": "weibo",
      "keywords": [
        "新"
      ],
      "collectedAt": "2026-06-28T05:12:33.618Z",
      "source": "weibo_hotSearch"
    },
    {
      "id": "auto_weibo_15af5921",
      "title": "玩家回应恋与深空回应",
      "url": "https://s.weibo.com/weibo?q=%23%E7%8E%A9%E5%AE%B6%E5%9B%9E%E5%BA%94%E6%81%8B%E4%B8%8E%E6%B7%B1%E7%A9%BA%E5%9B%9E%E5%BA%94%23",
      "platform": "weibo",
      "keywords": [
        "新"
      ],
      "collectedAt": "2026-06-28T05:12:33.618Z",
      "source": "weibo_hotSearch"
    },
    {
      "id": "auto_weibo_b99eed69",
      "title": "阿根廷任意球破门",
      "url": "https://s.weibo.com/weibo?q=%23%E9%98%BF%E6%A0%B9%E5%BB%B7%E4%BB%BB%E6%84%8F%E7%90%83%E7%A0%B4%E9%97%A8%23",
      "platform": "weibo",
      "keywords": [
        "新"
      ],
      "collectedAt": "2026-06-28T05:12:33.618Z",
      "source": "weibo_hotSearch"
    },
    {
      "id": "auto_weibo_950ee91c",
      "title": "甘南全部景区免门票为虚假消息",
      "url": "https://s.weibo.com/weibo?q=%23%E7%94%98%E5%8D%97%E5%85%A8%E9%83%A8%E6%99%AF%E5%8C%BA%E5%85%8D%E9%97%A8%E7%A5%A8%E4%B8%BA%E8%99%9A%E5%81%87%E6%B6%88%E6%81%AF%23",
      "platform": "weibo",
      "keywords": [],
      "collectedAt": "2026-06-28T05:12:33.618Z",
      "source": "weibo_hotSearch"
    },
    {
      "id": "auto_weibo_39841c6d",
      "title": "黄灿灿拿到全季通告费",
      "url": "https://s.weibo.com/weibo?q=%23%E9%BB%84%E7%81%BF%E7%81%BF%E6%8B%BF%E5%88%B0%E5%85%A8%E5%AD%A3%E9%80%9A%E5%91%8A%E8%B4%B9%23",
      "platform": "weibo",
      "keywords": [
        "热"
      ],
      "collectedAt": "2026-06-28T05:12:33.618Z",
      "source": "weibo_hotSearch"
    },
    {
      "id": "auto_weibo_4be78c18",
      "title": "结婚的时候没想到我天天回来吧",
      "url": "https://s.weibo.com/weibo?q=%23%E7%BB%93%E5%A9%9A%E7%9A%84%E6%97%B6%E5%80%99%E6%B2%A1%E6%83%B3%E5%88%B0%E6%88%91%E5%A4%A9%E5%A4%A9%E5%9B%9E%E6%9D%A5%E5%90%A7%23",
      "platform": "weibo",
      "keywords": [
        "新"
      ],
      "collectedAt": "2026-06-28T05:12:33.618Z",
      "source": "weibo_hotSearch"
    },
    {
      "id": "auto_weibo_9f1f642b",
      "title": "浪姐结束各回各咖",
      "url": "https://s.weibo.com/weibo?q=%23%E6%B5%AA%E5%A7%90%E7%BB%93%E6%9D%9F%E5%90%84%E5%9B%9E%E5%90%84%E5%92%96%23",
      "platform": "weibo",
      "keywords": [
        "新"
      ],
      "collectedAt": "2026-06-28T05:12:33.618Z",
      "source": "weibo_hotSearch"
    },
    {
      "id": "auto_weibo_33826f12",
      "title": "C罗半场数据",
      "url": "https://s.weibo.com/weibo?q=%23C%E7%BD%97%E5%8D%8A%E5%9C%BA%E6%95%B0%E6%8D%AE%23",
      "platform": "weibo",
      "keywords": [
        "新"
      ],
      "collectedAt": "2026-06-28T05:12:33.618Z",
      "source": "weibo_hotSearch"
    },
    {
      "id": "auto_weibo_68644799",
      "title": "李现 杨紫",
      "url": "https://s.weibo.com/weibo?q=%23%E6%9D%8E%E7%8E%B0%20%E6%9D%A8%E7%B4%AB%23",
      "platform": "weibo",
      "keywords": [
        "热"
      ],
      "collectedAt": "2026-06-28T05:12:33.618Z",
      "source": "weibo_hotSearch"
    },
    {
      "id": "auto_weibo_a13ceeab",
      "title": "迪丽热巴江坂丽奈美甲",
      "url": "https://s.weibo.com/weibo?q=%23%E8%BF%AA%E4%B8%BD%E7%83%AD%E5%B7%B4%E6%B1%9F%E5%9D%82%E4%B8%BD%E5%A5%88%E7%BE%8E%E7%94%B2%23",
      "platform": "weibo",
      "keywords": [],
      "collectedAt": "2026-06-28T05:12:33.618Z",
      "source": "weibo_hotSearch"
    },
    {
      "id": "auto_weibo_7bfc00c1",
      "title": "200万粉网红诋毁袁隆平水稻育种技术",
      "url": "https://s.weibo.com/weibo?q=%23200%E4%B8%87%E7%B2%89%E7%BD%91%E7%BA%A2%E8%AF%8B%E6%AF%81%E8%A2%81%E9%9A%86%E5%B9%B3%E6%B0%B4%E7%A8%BB%E8%82%B2%E7%A7%8D%E6%8A%80%E6%9C%AF%23",
      "platform": "weibo",
      "keywords": [],
      "collectedAt": "2026-06-28T05:12:33.618Z",
      "source": "weibo_hotSearch"
    },
    {
      "id": "auto_weibo_32c5ecc1",
      "title": "C罗倒钩被挡",
      "url": "https://s.weibo.com/weibo?q=%23C%E7%BD%97%E5%80%92%E9%92%A9%E8%A2%AB%E6%8C%A1%23",
      "platform": "weibo",
      "keywords": [],
      "collectedAt": "2026-06-28T05:12:33.618Z",
      "source": "weibo_hotSearch"
    },
    {
      "id": "auto_weibo_4a930dc",
      "title": "佛得角队长被曝因强奸指控接受调查",
      "url": "https://s.weibo.com/weibo?q=%23%E4%BD%9B%E5%BE%97%E8%A7%92%E9%98%9F%E9%95%BF%E8%A2%AB%E6%9B%9D%E5%9B%A0%E5%BC%BA%E5%A5%B8%E6%8C%87%E6%8E%A7%E6%8E%A5%E5%8F%97%E8%B0%83%E6%9F%A5%23",
      "platform": "weibo",
      "keywords": [],
      "collectedAt": "2026-06-28T05:12:33.618Z",
      "source": "weibo_hotSearch"
    },
    {
      "id": "auto_weibo_9e65cdb2",
      "title": "女儿毕业寄回几百斤包裹妈妈天塌了",
      "url": "https://s.weibo.com/weibo?q=%23%E5%A5%B3%E5%84%BF%E6%AF%95%E4%B8%9A%E5%AF%84%E5%9B%9E%E5%87%A0%E7%99%BE%E6%96%A4%E5%8C%85%E8%A3%B9%E5%A6%88%E5%A6%88%E5%A4%A9%E5%A1%8C%E4%BA%86%23",
      "platform": "weibo",
      "keywords": [],
      "collectedAt": "2026-06-28T05:12:33.618Z",
      "source": "weibo_hotSearch"
    },
    {
      "id": "auto_weibo_720f3f41",
      "title": "韩国淘汰",
      "url": "https://s.weibo.com/weibo?q=%23%E9%9F%A9%E5%9B%BD%E6%B7%98%E6%B1%B0%23",
      "platform": "weibo",
      "keywords": [
        "热"
      ],
      "collectedAt": "2026-06-28T05:12:33.618Z",
      "source": "weibo_hotSearch"
    },
    {
      "id": "auto_weibo_5344b8fc",
      "title": "美军对伊朗实施新一轮打击",
      "url": "https://s.weibo.com/weibo?q=%23%E7%BE%8E%E5%86%9B%E5%AF%B9%E4%BC%8A%E6%9C%97%E5%AE%9E%E6%96%BD%E6%96%B0%E4%B8%80%E8%BD%AE%E6%89%93%E5%87%BB%23",
      "platform": "weibo",
      "keywords": [],
      "collectedAt": "2026-06-28T05:12:33.618Z",
      "source": "weibo_hotSearch"
    },
    {
      "id": "auto_weibo_a7c3da66",
      "title": "英格兰不在欧洲玩了",
      "url": "https://s.weibo.com/weibo?q=%23%E8%8B%B1%E6%A0%BC%E5%85%B0%E4%B8%8D%E5%9C%A8%E6%AC%A7%E6%B4%B2%E7%8E%A9%E4%BA%86%23",
      "platform": "weibo",
      "keywords": [
        "新"
      ],
      "collectedAt": "2026-06-28T05:12:33.618Z",
      "source": "weibo_hotSearch"
    },
    {
      "id": "auto_weibo_a9e5a399",
      "title": "刘宇宁依赖摇最严厉的父亲",
      "url": "https://s.weibo.com/weibo?q=%23%E5%88%98%E5%AE%87%E5%AE%81%E4%BE%9D%E8%B5%96%E6%91%87%E6%9C%80%E4%B8%A5%E5%8E%89%E7%9A%84%E7%88%B6%E4%BA%B2%23",
      "platform": "weibo",
      "keywords": [
        "新"
      ],
      "collectedAt": "2026-06-28T05:12:33.618Z",
      "source": "weibo_hotSearch"
    },
    {
      "id": "auto_bilibili_9a2b322a",
      "title": "解读葡萄牙战平哥伦比亚",
      "url": "https://search.bilibili.com/all?keyword=%E8%A7%A3%E8%AF%BB%E8%91%A1%E8%90%84%E7%89%99%E6%88%98%E5%B9%B3%E5%93%A5%E4%BC%A6%E6%AF%94%E4%BA%9A",
      "platform": "bilibili",
      "keywords": [],
      "collectedAt": "2026-06-28T05:12:35.447Z",
      "source": "bilibili_trending_ranking"
    },
    {
      "id": "auto_weibo_56443949",
      "title": "老板暂停营业奉旨入京",
      "url": "https://s.weibo.com/weibo?q=%23%E8%80%81%E6%9D%BF%E6%9A%82%E5%81%9C%E8%90%A5%E4%B8%9A%E5%A5%89%E6%97%A8%E5%85%A5%E4%BA%AC%23",
      "platform": "weibo",
      "keywords": [
        "新"
      ],
      "collectedAt": "2026-06-28T05:12:33.618Z",
      "source": "weibo_hotSearch"
    },
    {
      "id": "auto_bilibili_682c0a5",
      "title": "完全小众的大理打开方式",
      "url": "https://search.bilibili.com/all?keyword=%E5%AE%8C%E5%85%A8%E5%B0%8F%E4%BC%97%E7%9A%84%E5%A4%A7%E7%90%86%E6%89%93%E5%BC%80%E6%96%B9%E5%BC%8F",
      "platform": "bilibili",
      "keywords": [],
      "collectedAt": "2026-06-28T05:12:35.447Z",
      "source": "bilibili_trending_ranking"
    },
    {
      "id": "auto_weibo_8448601a",
      "title": "甲亢哥得知葡萄牙可能要踢西法哭了",
      "url": "https://s.weibo.com/weibo?q=%23%E7%94%B2%E4%BA%A2%E5%93%A5%E5%BE%97%E7%9F%A5%E8%91%A1%E8%90%84%E7%89%99%E5%8F%AF%E8%83%BD%E8%A6%81%E8%B8%A2%E8%A5%BF%E6%B3%95%E5%93%AD%E4%BA%86%23",
      "platform": "weibo",
      "keywords": [
        "新"
      ],
      "collectedAt": "2026-06-28T05:12:33.618Z",
      "source": "weibo_hotSearch"
    },
    {
      "id": "auto_bilibili_e2698bec",
      "title": "韩国队世界杯惨遭淘汰",
      "url": "https://search.bilibili.com/all?keyword=%E9%9F%A9%E5%9B%BD%E9%98%9F%E4%B8%96%E7%95%8C%E6%9D%AF%E6%83%A8%E9%81%AD%E6%B7%98%E6%B1%B0",
      "platform": "bilibili",
      "keywords": [],
      "collectedAt": "2026-06-28T05:12:35.447Z",
      "source": "bilibili_trending_ranking"
    },
    {
      "id": "auto_weibo_78bf337",
      "title": "宁艺卓黑丝绒抹胸长裙",
      "url": "https://s.weibo.com/weibo?q=%23%E5%AE%81%E8%89%BA%E5%8D%93%E9%BB%91%E4%B8%9D%E7%BB%92%E6%8A%B9%E8%83%B8%E9%95%BF%E8%A3%99%23",
      "platform": "weibo",
      "keywords": [
        "新"
      ],
      "collectedAt": "2026-06-28T05:12:33.618Z",
      "source": "weibo_hotSearch"
    },
    {
      "id": "auto_bilibili_efe276cf",
      "title": "伊朗压哨出局",
      "url": "https://search.bilibili.com/all?keyword=%E4%BC%8A%E6%9C%97%E5%8E%8B%E5%93%A8%E5%87%BA%E5%B1%80",
      "platform": "bilibili",
      "keywords": [],
      "collectedAt": "2026-06-28T05:12:35.447Z",
      "source": "bilibili_trending_ranking"
    },
    {
      "id": "auto_weibo_586a8af",
      "title": "吴艳妮睡过头素颜去比赛",
      "url": "https://s.weibo.com/weibo?q=%23%E5%90%B4%E8%89%B3%E5%A6%AE%E7%9D%A1%E8%BF%87%E5%A4%B4%E7%B4%A0%E9%A2%9C%E5%8E%BB%E6%AF%94%E8%B5%9B%23",
      "platform": "weibo",
      "keywords": [
        "新"
      ],
      "collectedAt": "2026-06-28T05:12:33.618Z",
      "source": "weibo_hotSearch"
    },
    {
      "id": "auto_bilibili_1f5845f4",
      "title": "英格兰2-0巴拿马头名出线",
      "url": "https://search.bilibili.com/all?keyword=%E8%8B%B1%E6%A0%BC%E5%85%B02-0%E5%B7%B4%E6%8B%BF%E9%A9%AC%E5%A4%B4%E5%90%8D%E5%87%BA%E7%BA%BF",
      "platform": "bilibili",
      "keywords": [],
      "collectedAt": "2026-06-28T05:12:35.447Z",
      "source": "bilibili_trending_ranking"
    },
    {
      "id": "auto_weibo_342a8ea3",
      "title": "韩媒破防了",
      "url": "https://s.weibo.com/weibo?q=%23%E9%9F%A9%E5%AA%92%E7%A0%B4%E9%98%B2%E4%BA%86%23",
      "platform": "weibo",
      "keywords": [],
      "collectedAt": "2026-06-28T05:12:33.618Z",
      "source": "weibo_hotSearch"
    },
    {
      "id": "auto_bilibili_93f5226d",
      "title": "克罗地亚2-1加纳",
      "url": "https://search.bilibili.com/all?keyword=%E5%85%8B%E7%BD%97%E5%9C%B0%E4%BA%9A2-1%E5%8A%A0%E7%BA%B3",
      "platform": "bilibili",
      "keywords": [],
      "collectedAt": "2026-06-28T05:12:35.447Z",
      "source": "bilibili_trending_ranking"
    },
    {
      "id": "auto_weibo_cd434fc0",
      "title": "阿根廷世界杯首个丢球",
      "url": "https://s.weibo.com/weibo?q=%23%E9%98%BF%E6%A0%B9%E5%BB%B7%E4%B8%96%E7%95%8C%E6%9D%AF%E9%A6%96%E4%B8%AA%E4%B8%A2%E7%90%83%23",
      "platform": "weibo",
      "keywords": [
        "新"
      ],
      "collectedAt": "2026-06-28T05:12:33.618Z",
      "source": "weibo_hotSearch"
    },
    {
      "id": "auto_bilibili_153f56ba",
      "title": "凡人修仙传180集解析",
      "url": "https://search.bilibili.com/all?keyword=%E5%87%A1%E4%BA%BA%E4%BF%AE%E4%BB%99%E4%BC%A0180%E9%9B%86%E8%A7%A3%E6%9E%90",
      "platform": "bilibili",
      "keywords": [],
      "collectedAt": "2026-06-28T05:12:35.447Z",
      "source": "bilibili_trending_ranking"
    },
    {
      "id": "auto_weibo_eff505d0",
      "title": "黄灿灿 曾沛慈",
      "url": "https://s.weibo.com/weibo?q=%23%E9%BB%84%E7%81%BF%E7%81%BF%20%E6%9B%BE%E6%B2%9B%E6%85%88%23",
      "platform": "weibo",
      "keywords": [],
      "collectedAt": "2026-06-28T05:12:33.618Z",
      "source": "weibo_hotSearch"
    },
    {
      "id": "auto_bilibili_fbf00ce0",
      "title": "三角洲空气墙迷宫突破成功",
      "url": "https://search.bilibili.com/all?keyword=%E4%B8%89%E8%A7%92%E6%B4%B2%E7%A9%BA%E6%B0%94%E5%A2%99%E8%BF%B7%E5%AE%AB%E7%AA%81%E7%A0%B4%E6%88%90%E5%8A%9F",
      "platform": "bilibili",
      "keywords": [],
      "collectedAt": "2026-06-28T05:12:35.447Z",
      "source": "bilibili_trending_ranking"
    },
    {
      "id": "auto_weibo_f47241bc",
      "title": "恋与深空",
      "url": "https://s.weibo.com/weibo?q=%23%E6%81%8B%E4%B8%8E%E6%B7%B1%E7%A9%BA%23",
      "platform": "weibo",
      "keywords": [],
      "collectedAt": "2026-06-28T05:12:33.618Z",
      "source": "weibo_hotSearch"
    },
    {
      "id": "auto_bilibili_e8c5ee8a",
      "title": "和平精英夏日探险",
      "url": "https://search.bilibili.com/all?keyword=%E5%92%8C%E5%B9%B3%E7%B2%BE%E8%8B%B1%E5%A4%8F%E6%97%A5%E6%8E%A2%E9%99%A9",
      "platform": "bilibili",
      "keywords": [],
      "collectedAt": "2026-06-28T05:12:35.447Z",
      "source": "bilibili_trending_ranking"
    },
    {
      "id": "auto_weibo_85c7bb26",
      "title": "江淮汽车股价腰斩",
      "url": "https://s.weibo.com/weibo?q=%23%E6%B1%9F%E6%B7%AE%E6%B1%BD%E8%BD%A6%E8%82%A1%E4%BB%B7%E8%85%B0%E6%96%A9%23",
      "platform": "weibo",
      "keywords": [
        "新"
      ],
      "collectedAt": "2026-06-28T05:12:33.618Z",
      "source": "weibo_hotSearch"
    },
    {
      "id": "auto_bilibili_8089104f",
      "title": "曾沛慈李心洁神级舞台",
      "url": "https://search.bilibili.com/all?keyword=%E6%9B%BE%E6%B2%9B%E6%85%88%E6%9D%8E%E5%BF%83%E6%B4%81%E7%A5%9E%E7%BA%A7%E8%88%9E%E5%8F%B0",
      "platform": "bilibili",
      "keywords": [],
      "collectedAt": "2026-06-28T05:12:35.447Z",
      "source": "bilibili_trending_ranking"
    },
    {
      "id": "auto_weibo_d44beaa8",
      "title": "央视曝手机测评作弊乱象",
      "url": "https://s.weibo.com/weibo?q=%23%E5%A4%AE%E8%A7%86%E6%9B%9D%E6%89%8B%E6%9C%BA%E6%B5%8B%E8%AF%84%E4%BD%9C%E5%BC%8A%E4%B9%B1%E8%B1%A1%23",
      "platform": "weibo",
      "keywords": [],
      "collectedAt": "2026-06-28T05:12:33.618Z",
      "source": "weibo_hotSearch"
    },
    {
      "id": "auto_bilibili_2a0e8b14",
      "title": "夏促哪些顶级3A值得买",
      "url": "https://search.bilibili.com/all?keyword=%E5%A4%8F%E4%BF%83%E5%93%AA%E4%BA%9B%E9%A1%B6%E7%BA%A73A%E5%80%BC%E5%BE%97%E4%B9%B0",
      "platform": "bilibili",
      "keywords": [],
      "collectedAt": "2026-06-28T05:12:35.447Z",
      "source": "bilibili_trending_ranking"
    },
    {
      "id": "auto_weibo_d84d2a84",
      "title": "赵丽颖并非无戏可拍",
      "url": "https://s.weibo.com/weibo?q=%23%E8%B5%B5%E4%B8%BD%E9%A2%96%E5%B9%B6%E9%9D%9E%E6%97%A0%E6%88%8F%E5%8F%AF%E6%8B%8D%23",
      "platform": "weibo",
      "keywords": [],
      "collectedAt": "2026-06-28T05:12:33.618Z",
      "source": "weibo_hotSearch"
    },
    {
      "id": "auto_bilibili_90f222b0",
      "title": "佛得角 帝国从这里开始",
      "url": "https://search.bilibili.com/all?keyword=%E4%BD%9B%E5%BE%97%E8%A7%92%20%E5%B8%9D%E5%9B%BD%E4%BB%8E%E8%BF%99%E9%87%8C%E5%BC%80%E5%A7%8B",
      "platform": "bilibili",
      "keywords": [],
      "collectedAt": "2026-06-28T05:12:35.447Z",
      "source": "bilibili_trending_ranking"
    },
    {
      "id": "auto_weibo_b073f26d",
      "title": "韩国跪着死伊朗站着死",
      "url": "https://s.weibo.com/weibo?q=%23%E9%9F%A9%E5%9B%BD%E8%B7%AA%E7%9D%80%E6%AD%BB%E4%BC%8A%E6%9C%97%E7%AB%99%E7%9D%80%E6%AD%BB%23",
      "platform": "weibo",
      "keywords": [
        "新"
      ],
      "collectedAt": "2026-06-28T05:12:33.618Z",
      "source": "weibo_hotSearch"
    },
    {
      "id": "auto_bilibili_78a589fe",
      "title": "在B站与经典的另一种相逢",
      "url": "https://search.bilibili.com/all?keyword=%E5%9C%A8B%E7%AB%99%E4%B8%8E%E7%BB%8F%E5%85%B8%E7%9A%84%E5%8F%A6%E4%B8%80%E7%A7%8D%E7%9B%B8%E9%80%A2",
      "platform": "bilibili",
      "keywords": [],
      "collectedAt": "2026-06-28T05:12:35.447Z",
      "source": "bilibili_trending_ranking"
    },
    {
      "id": "auto_weibo_4170452c",
      "title": "穆祉丞打算干什么",
      "url": "https://s.weibo.com/weibo?q=%23%E7%A9%86%E7%A5%89%E4%B8%9E%E6%89%93%E7%AE%97%E5%B9%B2%E4%BB%80%E4%B9%88%23",
      "platform": "weibo",
      "keywords": [
        "新"
      ],
      "collectedAt": "2026-06-28T05:12:33.618Z",
      "source": "weibo_hotSearch"
    },
    {
      "id": "auto_bilibili_6e03c60",
      "title": "MSI全赛区终极前瞻",
      "url": "https://search.bilibili.com/all?keyword=MSI%E5%85%A8%E8%B5%9B%E5%8C%BA%E7%BB%88%E6%9E%81%E5%89%8D%E7%9E%BB",
      "platform": "bilibili",
      "keywords": [],
      "collectedAt": "2026-06-28T05:12:35.447Z",
      "source": "bilibili_trending_ranking"
    },
    {
      "id": "auto_weibo_585cd390",
      "title": "六问恋与深空",
      "url": "https://s.weibo.com/weibo?q=%23%E5%85%AD%E9%97%AE%E6%81%8B%E4%B8%8E%E6%B7%B1%E7%A9%BA%23",
      "platform": "weibo",
      "keywords": [],
      "collectedAt": "2026-06-28T05:12:33.618Z",
      "source": "weibo_hotSearch"
    },
    {
      "id": "auto_bilibili_ba444be1",
      "title": "硅谷101对话探月学校创始人",
      "url": "https://search.bilibili.com/all?keyword=%E7%A1%85%E8%B0%B7101%E5%AF%B9%E8%AF%9D%E6%8E%A2%E6%9C%88%E5%AD%A6%E6%A0%A1%E5%88%9B%E5%A7%8B%E4%BA%BA",
      "platform": "bilibili",
      "keywords": [],
      "collectedAt": "2026-06-28T05:12:35.447Z",
      "source": "bilibili_trending_ranking"
    },
    {
      "id": "auto_weibo_ebeca666",
      "title": "第一次对内蒙古地广人稀有了实感",
      "url": "https://s.weibo.com/weibo?q=%23%E7%AC%AC%E4%B8%80%E6%AC%A1%E5%AF%B9%E5%86%85%E8%92%99%E5%8F%A4%E5%9C%B0%E5%B9%BF%E4%BA%BA%E7%A8%80%E6%9C%89%E4%BA%86%E5%AE%9E%E6%84%9F%23",
      "platform": "weibo",
      "keywords": [],
      "collectedAt": "2026-06-28T05:12:33.618Z",
      "source": "weibo_hotSearch"
    },
    {
      "id": "auto_bilibili_5e1e93b4",
      "title": "Knock Out舞台好热血",
      "url": "https://search.bilibili.com/all?keyword=Knock%20Out%E8%88%9E%E5%8F%B0%E5%A5%BD%E7%83%AD%E8%A1%80",
      "platform": "bilibili",
      "keywords": [],
      "collectedAt": "2026-06-28T05:12:35.447Z",
      "source": "bilibili_trending_ranking"
    },
    {
      "id": "auto_weibo_4ba78f85",
      "title": "王中磊儿子冉莹颖儿子曹格儿子同框",
      "url": "https://s.weibo.com/weibo?q=%23%E7%8E%8B%E4%B8%AD%E7%A3%8A%E5%84%BF%E5%AD%90%E5%86%89%E8%8E%B9%E9%A2%96%E5%84%BF%E5%AD%90%E6%9B%B9%E6%A0%BC%E5%84%BF%E5%AD%90%E5%90%8C%E6%A1%86%23",
      "platform": "weibo",
      "keywords": [],
      "collectedAt": "2026-06-28T05:12:33.618Z",
      "source": "weibo_hotSearch"
    },
    {
      "id": "auto_bilibili_2d76fc4f",
      "title": "佛得角如何通过世界杯走向世界",
      "url": "https://search.bilibili.com/all?keyword=%E4%BD%9B%E5%BE%97%E8%A7%92%E5%A6%82%E4%BD%95%E9%80%9A%E8%BF%87%E4%B8%96%E7%95%8C%E6%9D%AF%E8%B5%B0%E5%90%91%E4%B8%96%E7%95%8C",
      "platform": "bilibili",
      "keywords": [],
      "collectedAt": "2026-06-28T05:12:35.447Z",
      "source": "bilibili_trending_ranking"
    },
    {
      "id": "auto_weibo_aea51077",
      "title": "阿尔及利亚3比3奥地利",
      "url": "https://s.weibo.com/weibo?q=%23%E9%98%BF%E5%B0%94%E5%8F%8A%E5%88%A9%E4%BA%9A3%E6%AF%943%E5%A5%A5%E5%9C%B0%E5%88%A9%23",
      "platform": "weibo",
      "keywords": [
        "新"
      ],
      "collectedAt": "2026-06-28T05:12:33.618Z",
      "source": "weibo_hotSearch"
    },
    {
      "id": "auto_bilibili_f0985860",
      "title": "波兰一喷泉被闪电击中",
      "url": "https://search.bilibili.com/all?keyword=%E6%B3%A2%E5%85%B0%E4%B8%80%E5%96%B7%E6%B3%89%E8%A2%AB%E9%97%AA%E7%94%B5%E5%87%BB%E4%B8%AD",
      "platform": "bilibili",
      "keywords": [],
      "collectedAt": "2026-06-28T05:12:35.447Z",
      "source": "bilibili_trending_ranking"
    },
    {
      "id": "auto_bilibili_dac1ab86",
      "title": "民主刚果3-1乌兹别克斯坦",
      "url": "https://search.bilibili.com/all?keyword=%E6%B0%91%E4%B8%BB%E5%88%9A%E6%9E%9C3-1%E4%B9%8C%E5%85%B9%E5%88%AB%E5%85%8B%E6%96%AF%E5%9D%A6",
      "platform": "bilibili",
      "keywords": [],
      "collectedAt": "2026-06-28T05:12:35.447Z",
      "source": "bilibili_trending_ranking"
    },
    {
      "id": "auto_bilibili_ecbcaf54",
      "title": "金建希涉嫌卖官鬻爵一审判刑7年",
      "url": "https://search.bilibili.com/all?keyword=%E9%87%91%E5%BB%BA%E5%B8%8C%E6%B6%89%E5%AB%8C%E5%8D%96%E5%AE%98%E9%AC%BB%E7%88%B5%E4%B8%80%E5%AE%A1%E5%88%A4%E5%88%917%E5%B9%B4",
      "platform": "bilibili",
      "keywords": [],
      "collectedAt": "2026-06-28T05:12:35.447Z",
      "source": "bilibili_trending_ranking"
    },
    {
      "id": "auto_bilibili_864eac70",
      "title": "韩立南宫婉互诉百年经历",
      "url": "https://search.bilibili.com/all?keyword=%E9%9F%A9%E7%AB%8B%E5%8D%97%E5%AE%AB%E5%A9%89%E4%BA%92%E8%AF%89%E7%99%BE%E5%B9%B4%E7%BB%8F%E5%8E%86",
      "platform": "bilibili",
      "keywords": [],
      "collectedAt": "2026-06-28T05:12:35.447Z",
      "source": "bilibili_trending_ranking"
    },
    {
      "id": "auto_bilibili_b8691c4b",
      "title": "阿根廷3-1约旦",
      "url": "https://search.bilibili.com/all?keyword=%E9%98%BF%E6%A0%B9%E5%BB%B73-1%E7%BA%A6%E6%97%A6",
      "platform": "bilibili",
      "keywords": [],
      "collectedAt": "2026-06-28T05:12:35.447Z",
      "source": "bilibili_trending_ranking"
    },
    {
      "id": "auto_bilibili_bcc183c6",
      "title": "浪姐决赛远走高飞全员乐队",
      "url": "https://search.bilibili.com/all?keyword=%E6%B5%AA%E5%A7%90%E5%86%B3%E8%B5%9B%E8%BF%9C%E8%B5%B0%E9%AB%98%E9%A3%9E%E5%85%A8%E5%91%98%E4%B9%90%E9%98%9F",
      "platform": "bilibili",
      "keywords": [],
      "collectedAt": "2026-06-28T05:12:35.447Z",
      "source": "bilibili_trending_ranking"
    },
    {
      "id": "auto_bilibili_c883395d",
      "title": "新疆小伙路西法回应走红",
      "url": "https://search.bilibili.com/all?keyword=%E6%96%B0%E7%96%86%E5%B0%8F%E4%BC%99%E8%B7%AF%E8%A5%BF%E6%B3%95%E5%9B%9E%E5%BA%94%E8%B5%B0%E7%BA%A2",
      "platform": "bilibili",
      "keywords": [],
      "collectedAt": "2026-06-28T05:12:35.447Z",
      "source": "bilibili_trending_ranking"
    },
    {
      "id": "auto_bilibili_503f2bad",
      "title": "AZ3全物资点位地图工具",
      "url": "https://search.bilibili.com/all?keyword=AZ3%E5%85%A8%E7%89%A9%E8%B5%84%E7%82%B9%E4%BD%8D%E5%9C%B0%E5%9B%BE%E5%B7%A5%E5%85%B7",
      "platform": "bilibili",
      "keywords": [],
      "collectedAt": "2026-06-28T05:12:35.447Z",
      "source": "bilibili_trending_ranking"
    },
    {
      "id": "auto_bilibili_98beedd1",
      "title": "黄霄雲定玄MV上线",
      "url": "https://search.bilibili.com/all?keyword=%E9%BB%84%E9%9C%84%E9%9B%B2%E5%AE%9A%E7%8E%84MV%E4%B8%8A%E7%BA%BF",
      "platform": "bilibili",
      "keywords": [],
      "collectedAt": "2026-06-28T05:12:35.447Z",
      "source": "bilibili_trending_ranking"
    },
    {
      "id": "auto_bilibili_18464add",
      "title": "桑多涅综合测评",
      "url": "https://search.bilibili.com/all?keyword=%E6%A1%91%E5%A4%9A%E6%B6%85%E7%BB%BC%E5%90%88%E6%B5%8B%E8%AF%84",
      "platform": "bilibili",
      "keywords": [],
      "collectedAt": "2026-06-28T05:12:35.447Z",
      "source": "bilibili_trending_ranking"
    },
    {
      "id": "auto_weibo_e9645a96",
      "title": "迪丽热巴蹲下和粉丝拍照",
      "url": "https://s.weibo.com/weibo?q=%23%E8%BF%AA%E4%B8%BD%E7%83%AD%E5%B7%B4%E8%B9%B2%E4%B8%8B%E5%92%8C%E7%B2%89%E4%B8%9D%E6%8B%8D%E7%85%A7%23",
      "platform": "weibo",
      "keywords": [
        "新"
      ],
      "collectedAt": "2026-06-28T05:12:33.618Z",
      "source": "weibo_hotSearch"
    },
    {
      "id": "auto_weibo_ab6d86c3",
      "title": "恋与深空回应",
      "url": "https://s.weibo.com/weibo?q=%23%E6%81%8B%E4%B8%8E%E6%B7%B1%E7%A9%BA%E5%9B%9E%E5%BA%94%23",
      "platform": "weibo",
      "keywords": [],
      "collectedAt": "2026-06-28T05:12:33.618Z",
      "source": "weibo_hotSearch"
    },
    {
      "id": "auto_weibo_93ba5a56",
      "title": "于正回应杨紫获奖",
      "url": "https://s.weibo.com/weibo?q=%23%E4%BA%8E%E6%AD%A3%E5%9B%9E%E5%BA%94%E6%9D%A8%E7%B4%AB%E8%8E%B7%E5%A5%96%23",
      "platform": "weibo",
      "keywords": [],
      "collectedAt": "2026-06-28T05:12:33.618Z",
      "source": "weibo_hotSearch"
    },
    {
      "id": "auto_weibo_6f4de640",
      "title": "肖战一天解锁两套Gucci超超季",
      "url": "https://s.weibo.com/weibo?q=%23%E8%82%96%E6%88%98%E4%B8%80%E5%A4%A9%E8%A7%A3%E9%94%81%E4%B8%A4%E5%A5%97Gucci%E8%B6%85%E8%B6%85%E5%AD%A3%23",
      "platform": "weibo",
      "keywords": [],
      "collectedAt": "2026-06-28T05:12:33.618Z",
      "source": "weibo_hotSearch"
    },
    {
      "id": "auto_weibo_1f29dc7",
      "title": "乌拉圭让球员自己坐飞机回国",
      "url": "https://s.weibo.com/weibo?q=%23%E4%B9%8C%E6%8B%89%E5%9C%AD%E8%AE%A9%E7%90%83%E5%91%98%E8%87%AA%E5%B7%B1%E5%9D%90%E9%A3%9E%E6%9C%BA%E5%9B%9E%E5%9B%BD%23",
      "platform": "weibo",
      "keywords": [],
      "collectedAt": "2026-06-28T05:12:33.618Z",
      "source": "weibo_hotSearch"
    },
    {
      "id": "auto_weibo_cccf000f",
      "title": "C罗任意球",
      "url": "https://s.weibo.com/weibo?q=%23C%E7%BD%97%E4%BB%BB%E6%84%8F%E7%90%83%23",
      "platform": "weibo",
      "keywords": [],
      "collectedAt": "2026-06-28T05:12:33.618Z",
      "source": "weibo_hotSearch"
    },
    {
      "id": "auto_weibo_82df8ed8",
      "title": "孙怡忘了自己33岁了",
      "url": "https://s.weibo.com/weibo?q=%23%E5%AD%99%E6%80%A1%E5%BF%98%E4%BA%86%E8%87%AA%E5%B7%B133%E5%B2%81%E4%BA%86%23",
      "platform": "weibo",
      "keywords": [],
      "collectedAt": "2026-06-28T05:12:33.618Z",
      "source": "weibo_hotSearch"
    },
    {
      "id": "auto_weibo_44db8934",
      "title": "东鹏饮料回应董事长不喝东鹏",
      "url": "https://s.weibo.com/weibo?q=%23%E4%B8%9C%E9%B9%8F%E9%A5%AE%E6%96%99%E5%9B%9E%E5%BA%94%E8%91%A3%E4%BA%8B%E9%95%BF%E4%B8%8D%E5%96%9D%E4%B8%9C%E9%B9%8F%23",
      "platform": "weibo",
      "keywords": [],
      "collectedAt": "2026-06-28T05:12:33.618Z",
      "source": "weibo_hotSearch"
    },
    {
      "id": "auto_weibo_af0f85cb",
      "title": "手机代码发现测评博主名字",
      "url": "https://s.weibo.com/weibo?q=%23%E6%89%8B%E6%9C%BA%E4%BB%A3%E7%A0%81%E5%8F%91%E7%8E%B0%E6%B5%8B%E8%AF%84%E5%8D%9A%E4%B8%BB%E5%90%8D%E5%AD%97%23",
      "platform": "weibo",
      "keywords": [
        "新"
      ],
      "collectedAt": "2026-06-28T05:12:33.618Z",
      "source": "weibo_hotSearch"
    },
    {
      "id": "auto_weibo_c3cef202",
      "title": "德国人为抢中国空调开始氪金了",
      "url": "https://s.weibo.com/weibo?q=%23%E5%BE%B7%E5%9B%BD%E4%BA%BA%E4%B8%BA%E6%8A%A2%E4%B8%AD%E5%9B%BD%E7%A9%BA%E8%B0%83%E5%BC%80%E5%A7%8B%E6%B0%AA%E9%87%91%E4%BA%86%23",
      "platform": "weibo",
      "keywords": [],
      "collectedAt": "2026-06-28T05:12:33.618Z",
      "source": "weibo_hotSearch"
    },
    {
      "id": "auto_weibo_f6582a57",
      "title": "闷热天不建议运动到大汗淋漓",
      "url": "https://s.weibo.com/weibo?q=%23%E9%97%B7%E7%83%AD%E5%A4%A9%E4%B8%8D%E5%BB%BA%E8%AE%AE%E8%BF%90%E5%8A%A8%E5%88%B0%E5%A4%A7%E6%B1%97%E6%B7%8B%E6%BC%93%23",
      "platform": "weibo",
      "keywords": [
        "新"
      ],
      "collectedAt": "2026-06-28T05:12:33.618Z",
      "source": "weibo_hotSearch"
    },
    {
      "id": "auto_weibo_69bca600",
      "title": "约旦1比3阿根廷",
      "url": "https://s.weibo.com/weibo?q=%23%E7%BA%A6%E6%97%A61%E6%AF%943%E9%98%BF%E6%A0%B9%E5%BB%B7%23",
      "platform": "weibo",
      "keywords": [
        "新"
      ],
      "collectedAt": "2026-06-28T05:12:33.618Z",
      "source": "weibo_hotSearch"
    },
    {
      "id": "auto_weibo_3fb8a7a8",
      "title": "乘风姐姐蓝调优雅力量",
      "url": "https://s.weibo.com/weibo?q=%23%E4%B9%98%E9%A3%8E%E5%A7%90%E5%A7%90%E8%93%9D%E8%B0%83%E4%BC%98%E9%9B%85%E5%8A%9B%E9%87%8F%23",
      "platform": "weibo",
      "keywords": [
        "新"
      ],
      "collectedAt": "2026-06-28T05:12:33.618Z",
      "source": "weibo_hotSearch"
    }
  ]
}
